easy_conf/__init__.py
easy_conf/config.py
sherilan_easy_conf-0.1.0.dist-info/METADATA
sherilan_easy_conf-0.1.0.dist-info/WHEEL
sherilan_easy_conf-0.1.0.dist-info/top_level.txt
sherilan_easy_conf-0.1.0.dist-info/RECORD
